seraphim/__init__.py
seraphim/api.py
seraphim/middleware.py
seraphim/orm.py
seraphim/response.py
seraphim-0.1.1.dist-info/LICENSE
seraphim-0.1.1.dist-info/METADATA
seraphim-0.1.1.dist-info/WHEEL
seraphim-0.1.1.dist-info/RECORD
