Metadata-Version: 2.1
Name: seraphim
Version: 0.1.1
Summary: Simple REST framework
License: LICENSE
Author: kaliv0
Author-email: kaloyan.ivanov88@gmail.com
Requires-Python: >=3.12,<4.0
Classifier: License :: Other/Proprietary License
Classifier: Programming Language :: Python :: 3
Requires-Dist: jinja2 (>=3.1.4,<4.0.0)
Requires-Dist: parse (>=1.20.2,<2.0.0)
Requires-Dist: webob (>=1.8.7,<2.0.0)
Requires-Dist: whitenoise (>=6.7.0,<7.0.0)
